COPYING.txt
MANIFEST.in
README.md
package_variables.py
requirements.txt
setup.py
lnns/__init__.py
lnns/lnns_plugin.py
lnns/core/__init__.py
lnns/core/network.py
lnns/images/lnns_logo.png
lnns/interfaces/__init__.py
lnns/interfaces/exports.py
lnns/interfaces/imports.py
lnns/interfaces/lnns.ui
lnns/interfaces/lnns_gui.py
lnns/interfaces/lnns_processing.py
lnns/interfaces/lnns_provider.py
lnns/interfaces/network_image_cli.py
lnns/interfaces/network_prn_cli.py
mlp_image_classifier.egg-info/PKG-INFO
mlp_image_classifier.egg-info/SOURCES.txt
mlp_image_classifier.egg-info/dependency_links.txt
mlp_image_classifier.egg-info/entry_points.txt
mlp_image_classifier.egg-info/top_level.txt