Metadata-Version: 2.1
Name: mlp-image-classifier
Version: 1.0.7
Summary: Supervised classification of an multi-band image using an MLP (Multi-Layer Perception) Neural Network Classifier. Based on the Neural Network MLPClassifier by scikit-learn. Dependencies: pyqtgraph, matplotlib and sklearn. See homepage for clear installation instructions.
Home-page: https://bitbucket.org/kul-reseco/lnns
Author: Ann Crabbé
Author-email: acrabbe.foss@gmail.com
License: UNKNOWN
Project-URL: Documentation, https://mlp-image-classifier.readthedocs.io
Project-URL: Source Code, https://bitbucket.org/kul-reseco/lnns/src
Project-URL: Issue Tracker, https://bitbucket.org/kul-reseco/lnns/issues
Keywords: supervised classification,neural network,remote sensing,mlp,multi-layer perception classifier,image classification
Platform: UNKNOWN
